pylsb_cli/__init__.py
pylsb_cli/__main__.py
pylsb_cli/bible_format.py
pylsb_cli/parse.py
pylsb_cli-1.1.0.dist-info/METADATA
pylsb_cli-1.1.0.dist-info/WHEEL
pylsb_cli-1.1.0.dist-info/entry_points.txt
pylsb_cli-1.1.0.dist-info/top_level.txt
pylsb_cli-1.1.0.dist-info/RECORD
