Metadata-Version: 2.1
Name: pylsb-cli
Version: 1.1.0
Summary: Command line interface for reading the Legacy Standard Bible.
Author-email: Matthew Rease <scubaventure101@hotmail.com>
License: GNU General Public License v3 (GPLv3)
Project-URL: Homepage, https://gitlab.com/Magicrafter13/pylsb-cli
Project-URL: Issues, https://gitlab.com/Magicrafter13/pylsb-cli/-/issues
Keywords: bible,lsb,cli,command line
Classifier: Development Status :: 5 - Production/Stable
Classifier: Environment :: Console
Classifier: Intended Audience :: End Users/Desktop
Classifier: License :: OSI Approved :: GNU General Public License v3 (GPLv3)
Classifier: Operating System :: OS Independent
Classifier: Programming Language :: Python :: 3
Classifier: Programming Language :: Python :: 3.9
Classifier: Programming Language :: Python :: 3.10
Classifier: Programming Language :: Python :: 3.11
Classifier: Programming Language :: Python :: 3.12
Classifier: Programming Language :: Python :: 3.13
Classifier: Topic :: Religion
Requires-Python: >=3.9
Requires-Dist: pylsb
